{
  "totalIterations" : 4,
  "iterations" : [ {
    "duration" : 244,
    "tokens" : { },
    "iterationNumber" : 1,
    "statusCode" : 200
  }, {
    "duration" : 223,
    "tokens" : {
      "total" : "1729"
    },
    "iterationNumber" : 2,
    "statusCode" : 200
  }, {
    "duration" : 247,
    "tokens" : {
      "total" : "2016"
    },
    "iterationNumber" : 3,
    "statusCode" : 200
  }, {
    "duration" : 216,
    "tokens" : {
      "total" : "2018"
    },
    "iterationNumber" : 4,
    "statusCode" : 200
  } ]
}